{
  "station_code": "44132",
  "source": {
    "latest_time_url": "https://www.jma.go.jp/bosai/amedas/data/latest_time.txt",
    "map_url": "https://www.jma.go.jp/bosai/amedas/data/map/20260220184000.json",
    "fetched_at": "2026-02-20T18:52:51.067531+09:00"
  },
  "data": {
    "pressure": [
      1015.2,
      0
    ],
    "normalPressure": [
      1018.2,
      0
    ],
    "temp": [
      7.2,
      0
    ],
    "humidity": [
      64,
      0
    ],
    "sun10m": [
      0,
      0
    ],
    "sun1h": [
      0.0,
      0
    ],
    "precipitation10m": [
      0.0,
      0
    ],
    "precipitation1h": [
      0.0,
      0
    ],
    "precipitation3h": [
      0.0,
      0
    ],
    "precipitation24h": [
      0.0,
      0
    ],
    "windDirection": [
      11,
      0
    ],
    "wind": [
      1.0,
      0
    ]
  }
}