{
  "station_code": "44132",
  "source": {
    "latest_time_url": "https://www.jma.go.jp/bosai/amedas/data/latest_time.txt",
    "map_url": "https://www.jma.go.jp/bosai/amedas/data/map/20260221133000.json",
    "fetched_at": "2026-02-21T13:43:32.729355+09:00"
  },
  "data": {
    "pressure": [
      1014.4,
      0
    ],
    "normalPressure": [
      1017.3,
      0
    ],
    "temp": [
      14.2,
      0
    ],
    "humidity": [
      42,
      0
    ],
    "sun10m": [
      10,
      0
    ],
    "sun1h": [
      1.0,
      0
    ],
    "precipitation10m": [
      0.0,
      0
    ],
    "precipitation1h": [
      0.0,
      0
    ],
    "precipitation3h": [
      0.0,
      0
    ],
    "precipitation24h": [
      0.0,
      0
    ],
    "windDirection": [
      3,
      0
    ],
    "wind": [
      1.0,
      0
    ]
  }
}