{
  "last_updated": "2026-04-04T00:50:09.234160+09:00",
  "sunrise": "05:25",
  "sunset": "18:03",
  "tide": [
    "05:47 (188cm)",
    "12:06 (5cm)",
    "18:49 (178cm)"
  ],
  "tide_hourly": [
    {
      "time": "00:00",
      "cm": 49.1
    },
    {
      "time": "00:20",
      "cm": 50.4
    },
    {
      "time": "00:40",
      "cm": 54
    },
    {
      "time": "01:00",
      "cm": 59.9
    },
    {
      "time": "01:20",
      "cm": 67.8
    },
    {
      "time": "01:40",
      "cm": 77.3
    },
    {
      "time": "02:00",
      "cm": 88.1
    },
    {
      "time": "02:20",
      "cm": 99.8
    },
    {
      "time": "02:40",
      "cm": 112
    },
    {
      "time": "03:00",
      "cm": 124.3
    },
    {
      "time": "03:20",
      "cm": 136.4
    },
    {
      "time": "03:40",
      "cm": 147.9
    },
    {
      "time": "04:00",
      "cm": 158.5
    },
    {
      "time": "04:20",
      "cm": 167.9
    },
    {
      "time": "04:40",
      "cm": 175.9
    },
    {
      "time": "05:00",
      "cm": 182
    },
    {
      "time": "05:20",
      "cm": 186.2
    },
    {
      "time": "05:40",
      "cm": 188.2
    },
    {
      "time": "06:00",
      "cm": 187.9
    },
    {
      "time": "06:20",
      "cm": 185.2
    },
    {
      "time": "06:40",
      "cm": 180.2
    },
    {
      "time": "07:00",
      "cm": 172.9
    },
    {
      "time": "07:20",
      "cm": 163.4
    },
    {
      "time": "07:40",
      "cm": 152.2
    },
    {
      "time": "08:00",
      "cm": 139.5
    },
    {
      "time": "08:20",
      "cm": 125.6
    },
    {
      "time": "08:40",
      "cm": 110.8
    },
    {
      "time": "09:00",
      "cm": 95.7
    },
    {
      "time": "09:20",
      "cm": 80.6
    },
    {
      "time": "09:40",
      "cm": 65.9
    },
    {
      "time": "10:00",
      "cm": 52.1
    },
    {
      "time": "10:20",
      "cm": 39.3
    },
    {
      "time": "10:40",
      "cm": 28.2
    },
    {
      "time": "11:00",
      "cm": 18.9
    },
    {
      "time": "11:20",
      "cm": 11.9
    },
    {
      "time": "11:40",
      "cm": 7.2
    },
    {
      "time": "12:00",
      "cm": 5.1
    },
    {
      "time": "12:20",
      "cm": 5.6
    },
    {
      "time": "12:40",
      "cm": 8.6
    },
    {
      "time": "13:00",
      "cm": 14.1
    },
    {
      "time": "13:20",
      "cm": 21.7
    },
    {
      "time": "13:40",
      "cm": 31.1
    },
    {
      "time": "14:00",
      "cm": 42
    },
    {
      "time": "14:20",
      "cm": 54
    },
    {
      "time": "14:40",
      "cm": 66.7
    },
    {
      "time": "15:00",
      "cm": 79.8
    },
    {
      "time": "15:20",
      "cm": 93
    },
    {
      "time": "15:40",
      "cm": 105.9
    },
    {
      "time": "16:00",
      "cm": 118.5
    },
    {
      "time": "16:20",
      "cm": 130.3
    },
    {
      "time": "16:40",
      "cm": 141.3
    },
    {
      "time": "17:00",
      "cm": 151.2
    },
    {
      "time": "17:20",
      "cm": 159.9
    },
    {
      "time": "17:40",
      "cm": 167
    },
    {
      "time": "18:00",
      "cm": 172.6
    },
    {
      "time": "18:20",
      "cm": 176.3
    },
    {
      "time": "18:40",
      "cm": 178.2
    },
    {
      "time": "19:00",
      "cm": 178.1
    },
    {
      "time": "19:20",
      "cm": 176.2
    },
    {
      "time": "19:40",
      "cm": 172.4
    },
    {
      "time": "20:00",
      "cm": 166.8
    },
    {
      "time": "20:20",
      "cm": 159.8
    },
    {
      "time": "20:40",
      "cm": 151.4
    },
    {
      "time": "21:00",
      "cm": 142
    },
    {
      "time": "21:20",
      "cm": 131.8
    },
    {
      "time": "21:40",
      "cm": 121.2
    },
    {
      "time": "22:00",
      "cm": 110.4
    },
    {
      "time": "22:20",
      "cm": 99.8
    },
    {
      "time": "22:40",
      "cm": 89.8
    },
    {
      "time": "23:00",
      "cm": 80.7
    },
    {
      "time": "23:20",
      "cm": 73
    },
    {
      "time": "23:40",
      "cm": 66.9
    },
    {
      "time": "24:00",
      "cm": 62.7
    }
  ],
  "tide_name": "大潮"
}