{
  "last_updated": "2026-06-30T02:45:57.994034+09:00",
  "sunrise": "04:28",
  "sunset": "19:00",
  "tide": [
    "04:13 (188cm)",
    "11:14 (20cm)",
    "18:36 (193cm)",
    "23:40 (111cm)"
  ],
  "tide_hourly": [
    {
      "time": "00:00",
      "cm": 121.8
    },
    {
      "time": "00:20",
      "cm": 126.7
    },
    {
      "time": "00:40",
      "cm": 132.6
    },
    {
      "time": "01:00",
      "cm": 139.3
    },
    {
      "time": "01:20",
      "cm": 146.3
    },
    {
      "time": "01:40",
      "cm": 153.6
    },
    {
      "time": "02:00",
      "cm": 160.6
    },
    {
      "time": "02:20",
      "cm": 167.3
    },
    {
      "time": "02:40",
      "cm": 173.4
    },
    {
      "time": "03:00",
      "cm": 178.6
    },
    {
      "time": "03:20",
      "cm": 182.9
    },
    {
      "time": "03:40",
      "cm": 185.9
    },
    {
      "time": "04:00",
      "cm": 187.7
    },
    {
      "time": "04:20",
      "cm": 187.9
    },
    {
      "time": "04:40",
      "cm": 186.6
    },
    {
      "time": "05:00",
      "cm": 183.6
    },
    {
      "time": "05:20",
      "cm": 179
    },
    {
      "time": "05:40",
      "cm": 172.8
    },
    {
      "time": "06:00",
      "cm": 165.2
    },
    {
      "time": "06:20",
      "cm": 156.1
    },
    {
      "time": "06:40",
      "cm": 146
    },
    {
      "time": "07:00",
      "cm": 134.8
    },
    {
      "time": "07:20",
      "cm": 123
    },
    {
      "time": "07:40",
      "cm": 110.7
    },
    {
      "time": "08:00",
      "cm": 98.3
    },
    {
      "time": "08:20",
      "cm": 85.9
    },
    {
      "time": "08:40",
      "cm": 73.8
    },
    {
      "time": "09:00",
      "cm": 62.3
    },
    {
      "time": "09:20",
      "cm": 51.7
    },
    {
      "time": "09:40",
      "cm": 42.2
    },
    {
      "time": "10:00",
      "cm": 34.2
    },
    {
      "time": "10:20",
      "cm": 27.8
    },
    {
      "time": "10:40",
      "cm": 23.2
    },
    {
      "time": "11:00",
      "cm": 20.7
    },
    {
      "time": "11:20",
      "cm": 20.2
    },
    {
      "time": "11:40",
      "cm": 21.8
    },
    {
      "time": "12:00",
      "cm": 25.3
    },
    {
      "time": "12:20",
      "cm": 30.7
    },
    {
      "time": "12:40",
      "cm": 37.6
    },
    {
      "time": "13:00",
      "cm": 46
    },
    {
      "time": "13:20",
      "cm": 55.4
    },
    {
      "time": "13:40",
      "cm": 65.8
    },
    {
      "time": "14:00",
      "cm": 76.8
    },
    {
      "time": "14:20",
      "cm": 88.2
    },
    {
      "time": "14:40",
      "cm": 100
    },
    {
      "time": "15:00",
      "cm": 111.8
    },
    {
      "time": "15:20",
      "cm": 123.5
    },
    {
      "time": "15:40",
      "cm": 135.1
    },
    {
      "time": "16:00",
      "cm": 146.1
    },
    {
      "time": "16:20",
      "cm": 156.5
    },
    {
      "time": "16:40",
      "cm": 166
    },
    {
      "time": "17:00",
      "cm": 174.4
    },
    {
      "time": "17:20",
      "cm": 181.5
    },
    {
      "time": "17:40",
      "cm": 187.1
    },
    {
      "time": "18:00",
      "cm": 191
    },
    {
      "time": "18:20",
      "cm": 193.3
    },
    {
      "time": "18:40",
      "cm": 193.8
    },
    {
      "time": "19:00",
      "cm": 192.7
    },
    {
      "time": "19:20",
      "cm": 189.9
    },
    {
      "time": "19:40",
      "cm": 185.6
    },
    {
      "time": "20:00",
      "cm": 180
    },
    {
      "time": "20:20",
      "cm": 173.3
    },
    {
      "time": "20:40",
      "cm": 165.7
    },
    {
      "time": "21:00",
      "cm": 157.5
    },
    {
      "time": "21:20",
      "cm": 149
    },
    {
      "time": "21:40",
      "cm": 140.6
    },
    {
      "time": "22:00",
      "cm": 132.7
    },
    {
      "time": "22:20",
      "cm": 125.5
    },
    {
      "time": "22:40",
      "cm": 119.6
    },
    {
      "time": "23:00",
      "cm": 115.1
    },
    {
      "time": "23:20",
      "cm": 112.2
    },
    {
      "time": "23:40",
      "cm": 111.2
    },
    {
      "time": "24:00",
      "cm": 112.1
    }
  ],
  "tide_name": "大潮"
}