{
  "last_updated": "2026-03-23T00:37:14.191296+09:00",
  "sunrise": "05:42",
  "sunset": "17:53",
  "tide": [
    "01:13 (64cm)",
    "06:56 (186cm)",
    "13:39 (2cm)",
    "20:28 (163cm)"
  ],
  "tide_hourly": [
    {
      "time": "00:00",
      "cm": 77.7
    },
    {
      "time": "00:20",
      "cm": 71.6
    },
    {
      "time": "00:40",
      "cm": 67.3
    },
    {
      "time": "01:00",
      "cm": 64.9
    },
    {
      "time": "01:20",
      "cm": 64.5
    },
    {
      "time": "01:40",
      "cm": 66.2
    },
    {
      "time": "02:00",
      "cm": 70.1
    },
    {
      "time": "02:20",
      "cm": 75.8
    },
    {
      "time": "02:40",
      "cm": 83.3
    },
    {
      "time": "03:00",
      "cm": 92.3
    },
    {
      "time": "03:20",
      "cm": 102.4
    },
    {
      "time": "03:40",
      "cm": 113.2
    },
    {
      "time": "04:00",
      "cm": 124.3
    },
    {
      "time": "04:20",
      "cm": 135.3
    },
    {
      "time": "04:40",
      "cm": 146
    },
    {
      "time": "05:00",
      "cm": 155.9
    },
    {
      "time": "05:20",
      "cm": 164.8
    },
    {
      "time": "05:40",
      "cm": 172.4
    },
    {
      "time": "06:00",
      "cm": 178.5
    },
    {
      "time": "06:20",
      "cm": 183
    },
    {
      "time": "06:40",
      "cm": 185.6
    },
    {
      "time": "07:00",
      "cm": 186.3
    },
    {
      "time": "07:20",
      "cm": 184.9
    },
    {
      "time": "07:40",
      "cm": 181.5
    },
    {
      "time": "08:00",
      "cm": 176
    },
    {
      "time": "08:20",
      "cm": 168.5
    },
    {
      "time": "08:40",
      "cm": 159.2
    },
    {
      "time": "09:00",
      "cm": 148.2
    },
    {
      "time": "09:20",
      "cm": 135.9
    },
    {
      "time": "09:40",
      "cm": 122.5
    },
    {
      "time": "10:00",
      "cm": 108.5
    },
    {
      "time": "10:20",
      "cm": 94.1
    },
    {
      "time": "10:40",
      "cm": 79.7
    },
    {
      "time": "11:00",
      "cm": 65.7
    },
    {
      "time": "11:20",
      "cm": 52.4
    },
    {
      "time": "11:40",
      "cm": 40.2
    },
    {
      "time": "12:00",
      "cm": 29.3
    },
    {
      "time": "12:20",
      "cm": 19.9
    },
    {
      "time": "12:40",
      "cm": 12.4
    },
    {
      "time": "13:00",
      "cm": 6.9
    },
    {
      "time": "13:20",
      "cm": 3.6
    },
    {
      "time": "13:40",
      "cm": 2.5
    },
    {
      "time": "14:00",
      "cm": 3.7
    },
    {
      "time": "14:20",
      "cm": 7.1
    },
    {
      "time": "14:40",
      "cm": 12.5
    },
    {
      "time": "15:00",
      "cm": 19.9
    },
    {
      "time": "15:20",
      "cm": 28.8
    },
    {
      "time": "15:40",
      "cm": 39.1
    },
    {
      "time": "16:00",
      "cm": 50.3
    },
    {
      "time": "16:20",
      "cm": 62.2
    },
    {
      "time": "16:40",
      "cm": 74.4
    },
    {
      "time": "17:00",
      "cm": 86.6
    },
    {
      "time": "17:20",
      "cm": 98.5
    },
    {
      "time": "17:40",
      "cm": 110
    },
    {
      "time": "18:00",
      "cm": 120.8
    },
    {
      "time": "18:20",
      "cm": 130.7
    },
    {
      "time": "18:40",
      "cm": 139.6
    },
    {
      "time": "19:00",
      "cm": 147.2
    },
    {
      "time": "19:20",
      "cm": 153.5
    },
    {
      "time": "19:40",
      "cm": 158.3
    },
    {
      "time": "20:00",
      "cm": 161.5
    },
    {
      "time": "20:20",
      "cm": 163.1
    },
    {
      "time": "20:40",
      "cm": 162.9
    },
    {
      "time": "21:00",
      "cm": 161.2
    },
    {
      "time": "21:20",
      "cm": 157.9
    },
    {
      "time": "21:40",
      "cm": 153.2
    },
    {
      "time": "22:00",
      "cm": 147.5
    },
    {
      "time": "22:20",
      "cm": 140.8
    },
    {
      "time": "22:40",
      "cm": 133.4
    },
    {
      "time": "23:00",
      "cm": 125.8
    },
    {
      "time": "23:20",
      "cm": 118
    },
    {
      "time": "23:40",
      "cm": 110.5
    },
    {
      "time": "24:00",
      "cm": 103.5
    }
  ],
  "tide_name": "中潮"
}